lobster_reconstructor/__init__.py
lobster_reconstructor/lobster_sim.py
lobster_reconstructor/ofi.py
lobster_reconstructor/orderbook.py
lobster_reconstructor/orders.py
lobster_reconstructor/utils.py
lobster_reconstructor-0.1.2.dist-info/licenses/LICENSE
lobster_reconstructor-0.1.2.dist-info/METADATA
lobster_reconstructor-0.1.2.dist-info/WHEEL
lobster_reconstructor-0.1.2.dist-info/top_level.txt
lobster_reconstructor-0.1.2.dist-info/RECORD
