Metadata-Version: 2.4
Name: lobster_reconstructor
Version: 0.1.2
Summary: A LOBSTER data limit order book simulator and analysis toolkit.
Author-email: Luc-Alexandre Fiechter <lucfiechter@g.ucla.edu>
License: MIT License
Project-URL: Homepage, https://github.com/Laffy03/Lobster_L3_orderbook_reconstructor
Project-URL: Documentation, https://lobster-l3-orderbook-reconstructor.readthedocs.io/en/latest/?badge=latest
Classifier: Programming Language :: Python :: 3
Classifier: License :: OSI Approved :: MIT License
Classifier: Operating System :: OS Independent
Classifier: Development Status :: 3 - Alpha
Classifier: Intended Audience :: Financial and Insurance Industry
Classifier: Intended Audience :: Science/Research
Classifier: Topic :: Office/Business :: Financial
Classifier: Topic :: Scientific/Engineering :: Mathematics
Requires-Python: >=3.10
License-File: LICENSE
Requires-Dist: numpy
Requires-Dist: pandas
Requires-Dist: plotly
Requires-Dist: dash
Requires-Dist: scipy
Requires-Dist: sortedcontainers
Dynamic: license-file
